tree_sitter_lsp/__init__.py
tree_sitter_lsp/_metainfo.py
tree_sitter_lsp/_version.py
tree_sitter_lsp/complete.py
tree_sitter_lsp/diagnose.py
tree_sitter_lsp/finders.py
tree_sitter_lsp/format.py
tree_sitter_lsp/misc.py
tree_sitter_lsp/schema.py
tree_sitter_lsp/utils.py
tree_sitter_lsp-0.0.14.dist-info/LICENSE
tree_sitter_lsp-0.0.14.dist-info/METADATA
tree_sitter_lsp-0.0.14.dist-info/WHEEL
tree_sitter_lsp-0.0.14.dist-info/top_level.txt
tree_sitter_lsp-0.0.14.dist-info/RECORD
