Metadata-Version: 2.1
Name: tree-sitter-lsp
Version: 0.0.14
Summary: a library to create language servers
Author-email: Wu Zhenyu <wuzhenyu@ustc.edu>
License: GPL v3
Project-URL: Homepage, https://tree-sitter-lsp.readthedocs.io
Project-URL: Download, https://github.com/neomutt/tree-sitter-lsp/releases
Project-URL: Bug Report, https://github.com/neomutt/tree-sitter-lsp/issues
Project-URL: Source, https://github.com/neomutt/tree-sitter-lsp
Keywords: language server,tree sitter,json schema
Classifier: Development Status :: 3 - Alpha
Classifier: Intended Audience :: Developers
Classifier: Topic :: Software Development :: Build Tools
Classifier: License :: OSI Approved :: GNU General Public License v3 (GPLv3)
Classifier: Operating System :: Microsoft :: Windows
Classifier: Operating System :: POSIX
Classifier: Operating System :: Unix
Classifier: Operating System :: MacOS
Classifier: Programming Language :: Python :: 3 :: Only
Classifier: Programming Language :: Python :: 3
Classifier: Programming Language :: Python :: 3.10
Classifier: Programming Language :: Python :: 3.11
Classifier: Programming Language :: Python :: 3.12
Classifier: Programming Language :: Python :: Implementation :: CPython
Classifier: Programming Language :: Python :: Implementation :: PyPy
Requires-Python: >=3.10
License-File: LICENSE
Requires-Dist: colorama
Requires-Dist: jinja2
Requires-Dist: jsonschema
Requires-Dist: pygls
Requires-Dist: tree-sitter
Provides-Extra: colorize
Requires-Dist: pygments ; extra == 'colorize'
Provides-Extra: dev
Requires-Dist: pytest-cov ; extra == 'dev'
Provides-Extra: misc
Requires-Dist: beautifulsoup4 ; extra == 'misc'
Requires-Dist: markdown-it-py ; extra == 'misc'
Requires-Dist: platformdirs ; extra == 'misc'
Requires-Dist: pypandoc ; extra == 'misc'
Provides-Extra: toml
Requires-Dist: tomli-w ; extra == 'toml'
Provides-Extra: yaml
Requires-Dist: pyyaml ; extra == 'yaml'
